agtool/__init__.py
agtool/utils/__init__.py
agtool/utils/path_utils.py
agtool-0.0.1.dist-info/LICENSE
agtool-0.0.1.dist-info/METADATA
agtool-0.0.1.dist-info/WHEEL
agtool-0.0.1.dist-info/top_level.txt
agtool-0.0.1.dist-info/RECORD
